pyttrading
