Metadata-Version: 2.1
Name: pyttrading
Version: 1.1.2
Summary: Trading Library
Author: CannavIT
Requires-Python: >=3.6
Requires-Dist: Backtesting==0.3.3
Requires-Dist: requests==2.32.3
Requires-Dist: pydantic==2.8.2
Requires-Dist: scipy==1.12.0
Requires-Dist: ta==0.11.0
